lurawi/__init__.py
lurawi/activity_manager.py
lurawi/calculate.py
lurawi/callbackmsg_manager.py
lurawi/compare.py
lurawi/custom_behaviour.py
lurawi/lurawi_agent.py
lurawi/remote_service.py
lurawi/timer_manager.py
lurawi/usermsg_manager.py
lurawi/utils.py
lurawi/webhook_handler.py
lurawi/workflow_engine.py
lurawi/workflow_service.py
lurawi/custom/behaviour_router.py
lurawi/custom/build_gpt_prompt.py
lurawi/custom/cache_conversation_history.py
lurawi/custom/chromadb_search.py
lurawi/custom/current_datetime.py
lurawi/custom/discord_message.py
lurawi/custom/file_loader.py
lurawi/custom/get_data_from_url.py
lurawi/custom/get_indexvalue.py
lurawi/custom/get_keyvalue.py
lurawi/custom/has_keyvalue.py
lurawi/custom/invoke_llm.py
lurawi/custom/populate_prompt.py
lurawi/custom/query_knowledgebase.py
lurawi/custom/random_picker.py
lurawi/custom/send_data_to_service_bus.py
lurawi/custom/send_data_to_url.py
lurawi/custom/text_input.py
lurawi/custom/user_file_upload.py
lurawi/custom/validate_with_regex.py
lurawi_agent-0.0.1.dist-info/METADATA
lurawi_agent-0.0.1.dist-info/WHEEL
lurawi_agent-0.0.1.dist-info/top_level.txt
lurawi_agent-0.0.1.dist-info/RECORD
