Metadata-Version: 2.1
Name: lurawi-agent
Version: 0.0.1
Summary: Lurawi Agents
Author-email: Xun Wang <wang.xun@gmail.com>
License: Apache License 2.0
Project-URL: Homepage, https://github.com/kunle12/Lurawi
Project-URL: Bug Tracker, https://github.com/kunle12/Lurawi
Classifier: Programming Language :: Python :: 3
Classifier: License :: OSI Approved :: MIT License
Classifier: Operating System :: OS Independent
Requires-Python: >=3.10
Requires-Dist: aiofiles
Requires-Dist: aiohttp
Requires-Dist: autogen-agentchat
Requires-Dist: azure-storage-blob
Requires-Dist: boto3
Requires-Dist: chromadb
Requires-Dist: fastapi
Requires-Dist: llama-cpp-python
Requires-Dist: multi-agent-orchestrator
Requires-Dist: openai
Requires-Dist: pandas
Requires-Dist: pdf2image
Requires-Dist: pillow
Requires-Dist: pycryptodome
Requires-Dist: pyjwt
Requires-Dist: requests
Requires-Dist: simplejson
Requires-Dist: tiktoken
